yugioh_timeless/__init__.py
yugioh_timeless/config.py
yugioh_timeless/interface.py
yugioh_timeless/timeless.py
yugioh_timeless-0.1.1b0.dist-info/licenses/LICENSE.md
yugioh_timeless-0.1.1b0.dist-info/METADATA
yugioh_timeless-0.1.1b0.dist-info/WHEEL
yugioh_timeless-0.1.1b0.dist-info/entry_points.txt
yugioh_timeless-0.1.1b0.dist-info/top_level.txt
yugioh_timeless-0.1.1b0.dist-info/RECORD
