Metadata-Version: 2.4
Name: yugioh-timeless
Version: 0.1.1b0
Summary: Custom format for the Yu-Gi-Oh! TCG
Author: Nace Zavrtanik
Maintainer-email: TIMELESS Nace <yugioh.timeless@gmail.com>
License-Expression: MIT
Project-URL: Homepage, https://yugioh-timeless.github.io
Project-URL: GitHub, https://github.com/nacezavrtanik/yugioh-timeless
Project-URL: YouTube, https://www.youtube.com/@Yu-Gi-OhTIMELESS
Keywords: yugioh,TCG,custom format,tournament
Classifier: Programming Language :: Python :: 3
Classifier: Programming Language :: Python :: 3 :: Only
Classifier: Programming Language :: Python :: 3.13
Classifier: Development Status :: 4 - Beta
Classifier: Intended Audience :: End Users/Desktop
Classifier: Operating System :: OS Independent
Classifier: Topic :: Games/Entertainment
Requires-Python: >=3.13
License-File: LICENSE.md
Requires-Dist: tabulate>=0.9.0
Dynamic: license-file
